script_args_parser/__init__.py
script_args_parser/arguments.py
script_args_parser/decorators.py
script_args_parser/parser.py
script_args_parser-0.4.1.dist-info/LICENSE
script_args_parser-0.4.1.dist-info/METADATA
script_args_parser-0.4.1.dist-info/WHEEL
script_args_parser-0.4.1.dist-info/RECORD
