Metadata-Version: 2.1
Name: script-args-parser
Version: 0.4.1
Summary: Script arguments parsing library.
Home-page: https://github.com/KRunchPL/script-args-parser
License: Apache-2.0
Author: KRunchPL
Author-email: krunchfrompoland@gmail.com
Requires-Python: >=3.9,<4.0
Classifier: License :: OSI Approved :: Apache Software License
Classifier: Programming Language :: Python :: 3
Classifier: Programming Language :: Python :: 3.9
Classifier: Programming Language :: Python :: 3.10
Classifier: Programming Language :: Python :: 3.11
Requires-Dist: PyYAML (>=6.0,<7.0)
Requires-Dist: toml (>=0.10.2,<0.11.0)
Project-URL: Documentation, https://github.com/KRunchPL/script-args-parser
Project-URL: Repository, https://github.com/KRunchPL/script-args-parser
